[
  {
    "date": "07-02-2022, 12:39",
    "username": "arhayrap",
    "isAdmin": false,
    "results": [
      {
        "url": "https://icms.cern.ch/tools/collaboration/institutes",
        "status": 200,
        "duration": 451,
        "load_time": 4676.620000042021,
        "warnings": [],
        "errors": [],
        "state": "OK"
      },
      {
        "url": "https://icms.cern.ch/tools/collaboration/mo-list",
        "status": 200,
        "duration": 403,
        "load_time": 3378.3649997785687,
        "warnings": [],
        "errors": [],
        "state": "OK"
      },
      {
        "url": "https://icms.cern.ch/tools/collaboration/statistics",
        "status": 200,
        "duration": 461,
        "load_time": 3464.8500001057982,
        "warnings": [],
        "errors": [],
        "state": "OK"
      },
      {
        "url": "https://icms.cern.ch/tools/collaboration/tenures",
        "status": 200,
        "duration": 377,
        "load_time": 3424.1249999031425,
        "warnings": [],
        "errors": [],
        "state": "OK"
      },
      {
        "url": "https://icms.cern.ch/tools/collaboration/cms-weeks/weeks",
        "status": 200,
        "duration": 453,
        "load_time": 3585.040000267327,
        "warnings": [],
        "errors": [
          "POST request error : 403  403 (Forbidden)"
        ],
        "state": "OK"
      },
      {
        "url": "https://icms.cern.ch/tools/collaboration/awards",
        "status": 200,
        "duration": 326,
        "load_time": 3141.5499998256564,
        "warnings": [],
        "errors": [
          "GET request error (main) : 500  500 (Internal Server Error)"
        ],
        "state": "OK"
      },
      {
        "url": "https://icms.cern.ch/tools/collaboration/job-openings",
        "status": 200,
        "duration": 504,
        "load_time": 2987.370000220835,
        "warnings": [],
        "errors": [
          "GET request error : 500  500 (Internal Server Error)",
          "GET request error : 500  500 (Internal Server Error)"
        ],
        "state": "OK"
      },
      {
        "url": "https://icms.cern.ch/tools/collaboration/questionnaires",
        "status": 200,
        "duration": 318,
        "load_time": 2761.5299997851253,
        "warnings": [],
        "errors": [
          "GET request error : 500  500 (Internal Server Error)"
        ],
        "state": "OK"
      },
      {
        "url": "https://icms.cern.ch/tools/institute/member-authors",
        "status": 200,
        "duration": 343,
        "load_time": 3213.2999999448657,
        "warnings": [],
        "errors": [],
        "state": "OK"
      },
      {
        "url": "https://icms.cern.ch/tools/administration/mo/mo-project-list",
        "status": 200,
        "duration": 324,
        "load_time": 2984.0449998155236,
        "warnings": [],
        "errors": [],
        "state": "OK"
      },
      {
        "url": "https://icms.cern.ch/tools/publications/cadi/awgs",
        "status": 200,
        "duration": 323,
        "load_time": 2787.4050000682473,
        "warnings": [],
        "errors": [],
        "state": "OK"
      },
      {
        "url": "https://icms.cern.ch/tools/publications/cadi/dashboard",
        "status": 200,
        "duration": 377,
        "load_time": 3606.0100002214313,
        "warnings": [],
        "errors": [],
        "state": "OK"
      }
    ],
    "cons_failed_pages": 0,
    "app_status": ""
  }
]