[
  {
    "date": "07-11-2022, 1:35",
    "username": "arhayrap",
    "isAdmin": false,
    "results": [
      {
        "url": "https://icms.cern.ch/tools/",
        "status": 200,
        "duration": 411,
        "load_time": 3508.889999706298,
        "warnings": [],
        "errors": [],
        "state": "OK"
      },
      {
        "url": "https://icms.cern.ch/tools/collaboration/people",
        "status": 200,
        "duration": 575,
        "load_time": 5742.20999982208,
        "warnings": [],
        "errors": [],
        "state": "OK"
      },
      {
        "url": "https://icms.cern.ch/tools/collaboration/applicants",
        "status": 200,
        "duration": 486,
        "load_time": 3279.7899995930493,
        "warnings": [],
        "errors": [],
        "state": "OK"
      },
      {
        "url": "https://icms.cern.ch/tools/collaboration/flags",
        "status": 200,
        "duration": 486,
        "load_time": 4285.690000280738,
        "warnings": [],
        "errors": [],
        "state": "OK"
      },
      {
        "url": "https://icms.cern.ch/tools/collaboration/communications",
        "status": 200,
        "duration": 446,
        "load_time": 4479.2200000956655,
        "warnings": [],
        "errors": [],
        "state": "OK"
      },
      {
        "url": "https://icms.cern.ch/tools/collaboration/cms-weeks/rooms",
        "status": 200,
        "duration": 469,
        "load_time": 3635.6099997647107,
        "warnings": [],
        "errors": [
          "POST request error : 403  403 (Forbidden)"
        ],
        "state": "OK"
      },
      {
        "url": "https://icms.cern.ch/tools/collaboration/awardees",
        "status": 200,
        "duration": 450,
        "load_time": 3048.1549999676645,
        "warnings": [],
        "errors": [],
        "state": "OK"
      },
      {
        "url": "https://icms.cern.ch/tools/collaboration/job-nominations",
        "status": 200,
        "duration": 465,
        "load_time": 3087.1850000694394,
        "warnings": [],
        "errors": [
          "GET request error : 500  500 (Internal Server Error)",
          "GET request error (main) : 500  500 (Internal Server Error)"
        ],
        "state": "OK"
      },
      {
        "url": "https://icms.cern.ch/tools/institute/profile",
        "status": 200,
        "duration": 520,
        "load_time": 4313.2600001990795,
        "warnings": [],
        "errors": [],
        "state": "OK"
      },
      {
        "url": "https://icms.cern.ch/tools/institute/suspensions",
        "status": 200,
        "duration": 543,
        "load_time": 2968.9850001595914,
        "warnings": [],
        "errors": [],
        "state": "OK"
      },
      {
        "url": "https://icms.cern.ch/tools/publications/cadi/lines",
        "status": 200,
        "duration": 444,
        "load_time": 3479.074999690056,
        "warnings": [],
        "errors": [],
        "state": "OK"
      },
      {
        "url": "https://icms.cern.ch/tools/publications/cadi/lines/approved",
        "status": 200,
        "duration": 733,
        "load_time": 3705.4349998943508,
        "warnings": [],
        "errors": [],
        "state": "OK"
      },
      {
        "url": "https://icms.cern.ch/tools/publications/cadi/check-latex-build",
        "status": 200,
        "duration": 635,
        "load_time": 3022.659999784082,
        "warnings": [],
        "errors": [],
        "state": "OK"
      },
      {
        "url": "https://icms.cern.ch/tools/publications/author-lists/author-data",
        "status": 200,
        "duration": 430,
        "load_time": 2889.295000117272,
        "warnings": [],
        "errors": [],
        "state": "OK"
      },
      {
        "url": "https://icms.cern.ch/tools/user/profile",
        "status": 200,
        "duration": 420,
        "load_time": 4984.539999626577,
        "warnings": [],
        "errors": [],
        "state": "OK"
      }
    ],
    "cons_failed_pages": 0,
    "app_status": ""
  }
]